suvvyapi/__init__.py
suvvyapi/_utils.py
suvvyapi/asynchronous/__init__.py
suvvyapi/asynchronous/wrapper.py
suvvyapi/enums/__init__.py
suvvyapi/exceptions/__init__.py
suvvyapi/exceptions/api.py
suvvyapi/history/__init__.py
suvvyapi/models/__init__.py
suvvyapi/models/history.py
suvvyapi/models/responses.py
suvvyapi/sync/__init__.py
suvvyapi/sync/wrapper.py
suvvyapi/wrapper/__init__.py
suvvyapi-1.0.2.dist-info/LICENSE
suvvyapi-1.0.2.dist-info/METADATA
suvvyapi-1.0.2.dist-info/WHEEL
suvvyapi-1.0.2.dist-info/RECORD
