Metadata-Version: 2.1
Name: suvvyapi
Version: 1.0.2
Summary: A Python API wrapper for Suvvy AI API
Home-page: https://github.com/suvvyai/suvvyapi
License: MIT
Keywords: python,wrapper,chatgpt,suvvy,ai,suvvyai
Author: Roman Poltorabatko
Author-email: barabum@duck.com
Requires-Python: >=3.10
Classifier: Intended Audience :: Developers
Classifier: License :: OSI Approved :: MIT License
Classifier: Operating System :: OS Independent
Classifier: Programming Language :: Python
Classifier: Programming Language :: Python :: 3
Classifier: Programming Language :: Python :: 3.10
Classifier: Programming Language :: Python :: 3.11
Classifier: Programming Language :: Python :: 3.12
Classifier: Topic :: Software Development :: Libraries :: Python Modules
Requires-Dist: deprecation (>=2.1.0,<3.0.0)
Requires-Dist: httpx (>=0.26.0,<0.27.0)
Requires-Dist: pydantic (>=2.5.3,<3.0.0)
Project-URL: Repository, https://github.com/suvvyai/suvvyapi
